picovdb/__init__.py
picovdb/pico_vdb.py
picovdb-0.2.1.dist-info/LICENSE
picovdb-0.2.1.dist-info/METADATA
picovdb-0.2.1.dist-info/WHEEL
picovdb-0.2.1.dist-info/RECORD
