Metadata-Version: 2.3
Name: picovdb
Version: 0.2.1
Summary: A tiny and fast local vector database in Python.
Author: Wensheng Wang
Author-email: wenshengwang@gmail.com
Requires-Python: >=3.10,<4.0
Classifier: Programming Language :: Python :: 3
Classifier: Programming Language :: Python :: 3.10
Classifier: Programming Language :: Python :: 3.11
Classifier: Programming Language :: Python :: 3.12
Classifier: Programming Language :: Python :: 3.13
Requires-Dist: numpy
Project-URL: Repository, https://github.com/wensheng/picovdb.git
